<PAMDataset>
  <PAMRasterBand band="1">
    <Metadata>
      <MDI key="STATISTICS_APPROXIMATE">YES</MDI>
      <MDI key="STATISTICS_MAXIMUM">237</MDI>
      <MDI key="STATISTICS_MEAN">110.31192924627</MDI>
      <MDI key="STATISTICS_MINIMUM">1</MDI>
      <MDI key="STATISTICS_STDDEV">32.960405894493</MDI>
      <MDI key="STATISTICS_VALID_PERCENT">82.35</MDI>
    </Metadata>
  </PAMRasterBand>
  <PAMRasterBand band="2">
    <Metadata>
      <MDI key="STATISTICS_APPROXIMATE">YES</MDI>
      <MDI key="STATISTICS_MAXIMUM">235</MDI>
      <MDI key="STATISTICS_MEAN">117.03484086014</MDI>
      <MDI key="STATISTICS_MINIMUM">1</MDI>
      <MDI key="STATISTICS_STDDEV">35.457299554956</MDI>
      <MDI key="STATISTICS_VALID_PERCENT">82.35</MDI>
    </Metadata>
  </PAMRasterBand>
  <PAMRasterBand band="3">
    <Metadata>
      <MDI key="STATISTICS_APPROXIMATE">YES</MDI>
      <MDI key="STATISTICS_MAXIMUM">255</MDI>
      <MDI key="STATISTICS_MEAN">113.01308963687</MDI>
      <MDI key="STATISTICS_MINIMUM">1</MDI>
      <MDI key="STATISTICS_STDDEV">29.319882858619</MDI>
      <MDI key="STATISTICS_VALID_PERCENT">82.39</MDI>
    </Metadata>
  </PAMRasterBand>
</PAMDataset>
